<?xml version="1.0" encoding="utf-8"?>
<odoo>
  <data noupdate="1">
    <!-- Aulas ocultas para uso interno -->
    <record id="aula_subidas" model="gestion_clases.aula">
      <field name="nombre">Subidas</field>
      <field name="centro">Virtual</field>
      <field name="visible_en_lista" eval="False"/>
    </record>

    <record id="aula_incidencias" model="gestion_clases.aula">
      <field name="nombre">Incidencias</field>
      <field name="centro">Virtual</field>
      <field name="visible_en_lista" eval="False"/>
    </record>
  </data>
</odoo>
